Metadata-Version: 2.1
Name: my_cool_lib_LK
Version: 0.1.0
Summary: Test library
Author: Lubos Kohut
Author-email: luboskohut.shop@gmail.com
License: GNU GPL
